.bumpversion.cfg
.gitignore
.gitlab-ci.yml
HACKING.md
LICENSE
README.md
manage.py
requirements.txt
setup.py
tox.ini
.githooks/pre-commit
.githooks/pre-push
.github/workflows/tox.yml
markdown_xblock/__init__.py
markdown_xblock/html.py
markdown_xblock/utils.py
markdown_xblock.egg-info/PKG-INFO
markdown_xblock.egg-info/SOURCES.txt
markdown_xblock.egg-info/dependency_links.txt
markdown_xblock.egg-info/entry_points.txt
markdown_xblock.egg-info/requires.txt
markdown_xblock.egg-info/top_level.txt
markdown_xblock/public/plugins/codemirror/LICENSE
markdown_xblock/public/plugins/codemirror/plugin.min.js
markdown_xblock/public/plugins/codemirror/source.html
markdown_xblock/public/plugins/codemirror/codemirror-4.8/addon/dialog/dialog.css
markdown_xblock/public/plugins/codemirror/codemirror-4.8/addon/dialog/dialog.js
markdown_xblock/public/plugins/codemirror/codemirror-4.8/addon/display/fullscreen.css
markdown_xblock/public/plugins/codemirror/codemirror-4.8/addon/display/fullscreen.js
markdown_xblock/public/plugins/codemirror/codemirror-4.8/addon/edit/matchbrackets.js
markdown_xblock/public/plugins/codemirror/codemirror-4.8/addon/search/search.js
markdown_xblock/public/plugins/codemirror/codemirror-4.8/addon/search/searchcursor.js
markdown_xblock/public/plugins/codemirror/codemirror-4.8/addon/selection/active-line.js
markdown_xblock/public/plugins/codemirror/codemirror-4.8/lib/codemirror.css
markdown_xblock/public/plugins/codemirror/codemirror-4.8/lib/codemirror.js
markdown_xblock/public/plugins/codemirror/codemirror-4.8/mode/css/css.js
markdown_xblock/public/plugins/codemirror/codemirror-4.8/mode/htmlmixed/htmlmixed.js
markdown_xblock/public/plugins/codemirror/codemirror-4.8/mode/javascript/javascript.js
markdown_xblock/public/plugins/codemirror/codemirror-4.8/mode/markdown/markdown.js
markdown_xblock/public/plugins/codemirror/codemirror-4.8/mode/xml/xml.js
markdown_xblock/public/plugins/codemirror/langs/en.js
markdown_xblock/public/plugins/codesample/plugin.min.js
markdown_xblock/public/plugins/codesample/css/prism.css
markdown_xblock/public/plugins/codesample/js/prism.js
markdown_xblock/public/plugins/image/plugin.min.js
markdown_xblock/public/plugins/link/plugin.min.js
