Metadata-Version: 2.4
Name: markdown-xblock
Version: 2.2.0
Summary: Markdown XBlock provides editing course content in Markdown.
Home-page: https://github.com/citynetwork/xblock-markdown
License: AGPL-3.0
Classifier: Development Status :: 4 - Beta
Classifier: Framework :: Django
Classifier: Intended Audience :: Education
Classifier: License :: OSI Approved :: GNU Affero General Public License v3
Classifier: Topic :: Education :: Computer Aided Instruction (CAI)
Classifier: Topic :: Education
Requires-Python: >=3.11
License-File: LICENSE
Requires-Dist: XBlock<5
Requires-Dist: markdown2>=2.3.9
Requires-Dist: Pygments>=2.0.1
Dynamic: classifier
Dynamic: description
Dynamic: description-content-type
Dynamic: home-page
Dynamic: license
Dynamic: license-file
Dynamic: requires-dist
Dynamic: requires-python
Dynamic: summary
